Workbook

Sheet Summary FR
A1: Empresa | B1: Empresa 1 | F1: Exchange Rate | H1: 7.6
B3: Refernce | C3: 2011 | D3: 2012 | E3: 2013 | F3: 2014 | G3: 2015
B4: Employees
B5: Women
B6: Men
B8: Year | C8: Revenue | D8: Costs | E8: Profit | F8: Increase Revenue | G8: Changes in Costs | H8: Changes in Profit
B9: 2011 | C9: =LOOKUP($B$1,Tabla381011241726[Empresa],Tabla381011241726[2011])/H1 -> 531195.54 | D9: =C9-E9 -> 430977.84 | E9: =LOOKUP($B$1,Tabla3810112417265[Empresa],Tabla3810112417265[2011])/$H$1 -> 100217.71
B10: 2012 | C10: =LOOKUP($B$1,Tabla381011241726[Empresa],Tabla381011241726[2012])/H1 -> 429382.33 | D10: =C10-E10 -> 353314.29 | E10: =LOOKUP($B$1,Tabla3810112417265[Empresa],Tabla3810112417265[2012])/$H$1 -> 76068.033 | F10: =IF(C9=0,0,(Tabla11[[#This Row],[Revenue]]-C9)/C9) -> -0.19166805 | G10: =IF(D9=0,0,(Tabla11[[#This Row],[Costs]]-D9)/D9) -> -0.1802031 | H10: =IF(E9=0,0,(Tabla11[[#This Row],[Profit]]-E9)/E9) -> -0.24097212
B11: 2013 | C11: =LOOKUP($B$1,Tabla381011241726[Empresa],Tabla381011241726[2013])/H1 -> 456825.25 | D11: =C11-E11 -> 378856.79 | E11: =LOOKUP($B$1,Tabla3810112417265[Empresa],Tabla3810112417265[2013])/$H$1 -> 77968.454 | F11: =IF(C10=0,0,(Tabla11[[#This Row],[Revenue]]-C10)/C10) -> 0.063912548 | G11: =IF(D10=0,0,(Tabla11[[#This Row],[Costs]]-D10)/D10) -> 0.072293982 | H11: =IF(E10=0,0,(Tabla11[[#This Row],[Profit]]-E10)/E10) -> 0.024983176
B12: 2014 | C12: =LOOKUP($B$1,Tabla381011241726[Empresa],Tabla381011241726[2014])/H1 -> 540066 | D12: =C12-E12 -> 467584.44 | E12: =LOOKUP($B$1,Tabla3810112417265[Empresa],Tabla3810112417265[2014])/$H$1 -> 72481.561 | F12: =IF(C11=0,0,(Tabla11[[#This Row],[Revenue]]-C11)/C11) -> 0.18221574 | G12: =IF(D11=0,0,(Tabla11[[#This Row],[Costs]]-D11)/D11) -> 0.23419837 | H12: =IF(E11=0,0,(Tabla11[[#This Row],[Profit]]-E11)/E11) -> -0.070373249
B13: 2015 | C13: =LOOKUP($B$1,Tabla381011241726[Empresa],Tabla381011241726[2015])/H1 -> 563184.06 | D13: =C13-E13 -> 436067.14 | E13: =LOOKUP($B$1,Tabla3810112417265[Empresa],Tabla3810112417265[2015])/$H$1 -> 127116.92 | F13: =IF(C12=0,0,(Tabla11[[#This Row],[Revenue]]-C12)/C12) -> 0.042805987 | G13: =IF(D12=0,0,(Tabla11[[#This Row],[Costs]]-D12)/D12) -> -0.067404505 | H13: =IF(E12=0,0,(Tabla11[[#This Row],[Profit]]-E12)/E12) -> 0.75378282
B16: Year | C16: Revenue | D16: Costs | E16: Profit
B17: 2011 | C17: =C9*$H$1 -> 4037086.1 | D17: =D9*$H$1 -> 3275431.6 | E17: =E9*$H$1 -> 761654.57
B18: 2012 | C18: =C10*$H$1 -> 3263305.7 | D18: =D10*$H$1 -> 2685188.6 | E18: =E10*$H$1 -> 578117.05
B19: 2013 | C19: =C11*$H$1 -> 3471871.9 | D19: =D11*$H$1 -> 2879311.6 | E19: =E11*$H$1 -> 592560.25
B20: 2014 | C20: =C12*$H$1 -> 4104501.6 | D20: =D12*$H$1 -> 3553641.7 | E20: =E12*$H$1 -> 550859.86
B21: 2015 | C21: =C13*$H$1 -> 4280198.8 | D21: =D13*$H$1 -> 3314110.3 | E21: =E13*$H$1 -> 966088.56
B23: Instrucciones:
B24: Esta hoja de excel le permite hacer una analisis por empresa, en la celda B1 usted puede ir modificando la celda de acuerdo a la empresa que esta evaluando
B25: Debera realizar 2 graficas, completar la tabla de Empleados y un responder a las preguntas al final de estas instrucciones.
B27: Lookup
B28: Llene la tabla de empleados de acuerdo a la empresa que seleccione en la celda B1
B29: * Hint: siilar al llenado de la table de Revenue-Costs-Profit
B31: Grafica 1
B32: Grafique una comparacion de los ingresos, Costos y Utilidades. Durante los años 2011 a 2015
B33: Agregue una linea de tendencia
B34: Realize la grafica lo mas completa y clara que considere puede dar una buena idea de la tendencia de la empresa, coloquela en la celda K10
B36: Grafica 2
B37: Grafique los empleados de la empresa durante los años 2011-2015 agregando el porcentaje que corresponde a mujeres
... B46: Si usted fuera una ONG que apoya a las empresas que contratan mujeres, seleccione dos empresas que apoyaría e indique porque?

Sheet Employees
B1: Souce | C1: EMPLEADOS EN LA EMPRESA
A2: COD | B2: Empresa | C2: 2011 | D2: 2012 | E2: 2013 | F2: 2014 | G2: 2015
A3: E-01 | B3: Empresa 1 | C3: 19 | D3: 21 | E3: 22 | F3: 19 | G3: 25
A4: E-02 | B4: Empresa 2 | C4: 7 | D4: 4 | E4: 5 | F4: 7 | G4: 12
A5: E-03 | B5: Empresa 3 | C5: 27 | D5: 34 | E5: 30 | F5: 36 | G5: 30
A6: E-04 | B6: Empresa 4 | C6: 7 | D6: 7 | E6: 7 | F6: 10 | G6: 8
A7: E-05 | B7: Empresa 5 | C7: 5 | D7: 7 | E7: 7 | F7: 8 | G7: 12
A8: E-06 | B8: Empresa 6 | E8: 30 | F8: 38 | G8: 35
A9: E-07 | B9: Empresa 7 | C9: 5 | D9: 3 | E9: 6 | F9: 10 | G9: 2
A10: E-08 | B10: Empresa 8 | C10: 42 | D10: 38 | E10: 45 | F10: 50 | G10: 26
A11: E-09 | B11: Empresa 9 | C11: 28 | D11: 30 | E11: 35 | F11: 40 | G11: 38
A12: E-10 | B12: Empresa 10 | C12: 6 | D12: 8 | E12: 10 | F12: 12 | G12: 15
A13: E-11 | B13: Empresa 11 | C13: 5 | D13: 7 | E13: 8 | F13: 12 | G13: 15
A14: E-12 | B14: Empresa 12 | C14: 9 | D14: 9 | E14: 11 | F14: 15 | G14: 15
A15: E-13 | B15: Empresa 13 | C15: 6 | D15: 11 | E15: 14 | F15: 15 | G15: 21
A16: E-14 | B16: Empresa 14 | D16: 9 | E16: 11 | F16: 13 | G16: 14
A17: E-15 | B17: Empresa 15 | C17: 17 | D17: 20 | E17: 25 | F17: 32 | G17: 33
A18: E-16 | B18: Empresa 16 | C18: 15 | D18: 27 | E18: 33 | F18: 34 | G18: 35
A19: E-17 | B19: Empresa 17 | F19: 13 | G19: 12
A20: E-18 | B20: Empresa 18 | C20: 9 | D20: 7 | E20: 19 | F20: 15 | G20: 16
A21: E-19 | B21: Empresa 19 | C21: 8 | D21: 7 | E21: 6 | F21: 21 | G21: 20
A22: E-20 | B22: Empresa 20 | C22: 15 | D22: 14 | E22: 13 | F22: 12 | G22: 11

Sheet Employees (W)
B1: EMPLEADAS MUJERES EN LA EMPRESA | G1: BF
A2: COD | B2: Empresa | C2: 2011 | D2: 2012 | E2: 2013 | F2: 2014 | G2: 2015
A3: E-01 | B3: Empresa 1 | C3: 11 | D3: 10 | E3: 7 | F3: 7 | G3: 6
A4: E-02 | B4: Empresa 2 | C4: 1 | D4: 1 | E4: 1 | F4: 4 | G4: 2
A5: E-03 | B5: Empresa 3 | C5: 7 | D5: 7 | E5: 4 | F5: 7 | G5: 6
A6: E-04 | B6: Empresa 4 | C6: 4 | D6: 3 | E6: 3 | F6: 4 | G6: 4
A7: E-05 | B7: Empresa 5 | C7: 2 | D7: 3 | E7: 3 | F7: 4 | G7: 4
A8: E-06 | B8: Empresa 6 | E8: 10 | F8: 14 | G8: 14
A9: E-07 | B9: Empresa 7 | C9: 1 | D9: 0 | E9: 0 | F9: 2 | G9: 2
A10: E-08 | B10: Empresa 8 | C10: 27 | D10: 22 | E10: 21 | F10: 34 | G10: 25
A11: E-09 | B11: Empresa 9 | C11: 6 | D11: 8 | E11: 10 | F11: 12 | G11: 10
A12: E-10 | B12: Empresa 10 | C12: 3 | D12: 3 | E12: 4 | F12: 5 | G12: 5
A13: E-11 | B13: Empresa 11 | C13: 1 | D13: 1 | E13: 2 | F13: 3 | G13: 3
A14: E-12 | B14: Empresa 12 | C14: 8 | D14: 8 | E14: 10 | F14: 14 | G14: 14
A15: E-13 | B15: Empresa 13 | C15: 2 | D15: 3 | E15: 4 | F15: 3 | G15: 3
A16: E-14 | B16: Empresa 14 | D16: 4 | E16: 4 | F16: 5 | G16: 5
A17: E-15 | B17: Empresa 15 | C17: 5 | D17: 5 | E17: 6 | F17: 6 | G17: 6
A18: E-16 | B18: Empresa 16 | C18: 4 | D18: 16 | E18: 15 | F18: 12 | G18: 12
A19: E-17 | B19: Empresa 17 | F19: 4 | G19: 4
A20: E-18 | B20: Empresa 18 | C20: 9 | D20: 6 | E20: 17 | F20: 12 | G20: 12
A21: E-19 | B21: Empresa 19 | C21: 1 | D21: 2 | E21: 2 | F21: 7 | G21: 7
A22: E-20 | B22: Empresa 20 | C22: 1 | D22: 4 | E22: 5 | F22: 11 | G22: 11

Sheet Revenue
A1: COD | B1: Empresa | C1: 2011 | D1: 2012 | E1: 2013 | F1: 2014 | G1: 2015
A2: E-01 | B2: Empresa 1 | C2: 4037086.1 | D2: 3263305.7 | E2: 3471871.9 | F2: 4104501.6 | G2: 4280198.8
A3: E-02 | B3: Empresa 2 | C3: 56896 | D3: 112462 | E3: 253249 | F3: 885562 | G3: 1067777
A4: E-03 | B4: Empresa 3 | C4: 4604811.6 | D4: 5348772.3 | E4: 7066122.9 | F4: 5138394.1 | G4: 5263896
A5: E-04 | B5: Empresa 4 | C5: 3276283 | D5: 5527963 | E5: 1700393.8 | F5: 3071869.9 | G5: 2577707
A6: E-05 | B6: Empresa 5 | C6: 783117 | D6: 733954.79 | E6: 1000894.6 | F6: 1403628.3 | G6: 1964214
A7: E-06 | B7: Empresa 6 | E7: 6828497 | F7: 9346087 | G7: 11800687
A8: E-07 | B8: Empresa 7 | C8: 569879 | D8: 1677191.4 | E8: 602423.8 | F8: 1591374.5 | G8: 4143640.9
A9: E-08 | B9: Empresa 8 | C9: 11129773 | D9: 8486513 | E9: 9216534 | F9: 10331016 | G9: 11000000
A10: E-09 | B10: Empresa 9 | C10: 12000000 | D10: 15000000 | E10: 18000000 | F10: 21350000 | G10: 24000000
A11: E-10 | B11: Empresa 10 | C11: 936250 | D11: 1105100 | E11: 1200500 | F11: 1355200 | G11: 1110073
A12: E-11 | B12: Empresa 11 | C12: 568978 | D12: 2568741 | E12: 1757154.6 | F12: 1406482.3 | G12: 2376688
A13: E-12 | B13: Empresa 12 | C13: 1591018.5 | D13: 1830630.9 | E13: 2362421 | F13: 2627424 | G13: 2569874
A14: E-13 | B14: Empresa 13 | C14: 172383 | D14: 660627 | E14: 733153 | F14: 1401600 | G14: 1643550
A15: E-14 | B15: Empresa 14 | D15: 1152473.1 | E15: 1259344 | F15: 1265302.6 | G15: 1784614
A16: E-15 | B16: Empresa 15 | C16: 3935713 | D16: 6640186 | E16: 7827607.2 | F16: 7023000 | G16: 8240000
A17: E-16 | B17: Empresa 16 | C17: 568941 | D17: 1928136.1 | E17: 2206398.5 | F17: 2904678.1 | G17: 5152144
A18: E-17 | B18: Empresa 17 | F18: 2686749 | G18: 2987415
A19: E-18 | B19: Empresa 18 | C19: 1284490.5 | D19: 1543814.5 | E19: 2049523.8 | F19: 2399611.2 | G19: 653840
A20: E-19 | B20: Empresa 19 | C20: 356871 | D20: 2578131 | E20: 3512790.1 | F20: 4522000 | G20: 3224000
A21: E-20 | B21: Empresa 20 | C21: 256871 | D21: 658745 | E21: 758946 | F21: 1343525 | G21: 1789832

Sheet Costs
A1: COD | B1: Empresa | C1: 2011 | D1: 2012 | E1: 2013 | F1: 2014 | G1: 2015
A2: E-01 | B2: Empresa 1 | C2: 3275431.6 | D2: 2685188.6 | E2: 2879311.6 | F2: 3553641.7 | G2: 3314110.3
A3: E-02 | B3: Empresa 2 | C3: 5544 | D3: 505624 | E3: 415488 | F3: 842657 | G3: 1016425
A4: E-03 | B4: Empresa 3 | C4: 4352105.5 | D4: 5118565.4 | E4: 6131759.9 | F4: 4075857.1 | G4: 4338598
A5: E-04 | B5: Empresa 4 | C5: 3156185 | D5: 5321131 | E5: 1641150.6 | F5: 2837373.8 | G5: 2347603
A6: E-05 | B6: Empresa 5 | C6: 743961 | D6: 646516.45 | E6: 938434.6 | F6: 1378851.2 | G6: 1728508
A7: E-06 | B7: Empresa 6 | E7: 4595624 | F7: 7113214 | G7: 9567814
A8: E-07 | B8: Empresa 7 | C8: 669679 | D8: 1593331.9 | E8: 566278.36 | F8: 1479978.2 | G8: 3646404
A9: E-08 | B9: Empresa 8 | C9: 10859773 | D9: 8203513 | E9: 8805534 | F9: 10071016 | G9: 10730000
A10: E-09 | B10: Empresa 9 | C10: 10800000 | D10: 13400000 | E10: 16000000 | F10: 20340000 | G10: 22950000
A11: E-10 | B11: Empresa 10 | C11: 664738 | D11: 784621 | E11: 852355 | F11: 962192 | G11: 951670
A12: E-11 | B12: Empresa 11 | C12: 67978 | D12: 2168147 | E12: 1636617.5 | F12: 1337669.5 | G12: 2098316
A13: E-12 | B13: Empresa 12 | C13: 1519259.8 | D13: 1665232.3 | E13: 1900879 | F13: 2244058 | G13: 2567812
A14: E-13 | B14: Empresa 13 | C14: 222383 | D14: 710627 | E14: 712720 | F14: 1269352 | G14: 1348500
A15: E-14 | B15: Empresa 14 | D15: 460988.8 | E15: 503737.6 | F15: 506121.09 | G15: 1487231
A16: E-15 | B16: Empresa 15 | C16: 3902398 | D16: 6399454 | E16: 7489471.2 | F16: 6788509.1 | G16: 7540000
A17: E-16 | B17: Empresa 16 | C17: 659941 | D17: 1783445.9 | E17: 2049724.2 | F17: 2701240.7 | G17: 4888450
A18: E-17 | B18: Empresa 17 | F18: 2670532 | G18: 2589712
A19: E-18 | B19: Empresa 18 | C19: 1025092.8 | D19: 1148792.5 | E19: 1391020.6 | F19: 1547077.9 | G19: 262993
A20: E-19 | B20: Empresa 19 | C20: 346971 | D20: 2377132 | E20: 3432790.1 | F20: 4122000 | G20: 5264782
A21: E-20 | B21: Empresa 20 | C21: 356676 | D21: 538746 | E21: 857936 | F21: 1543555 | G21: 1568791

Sheet Profit
A1: COD | B1: Empresa | C1: 2011 | D1: 2012 | E1: 2013 | F1: 2014 | G1: 2015
A2: E-01 | B2: Empresa 1 | C2: =Tabla381011241726[[#This Row],[2011]]-Tabla38101124172656[[#This Row],[2011]] -> 761654.57 | D2: =Tabla381011241726[[#This Row],[2012]]-Tabla38101124172656[[#This Row],[2012]] -> 578117.05 | E2: =Tabla381011241726[[#This Row],[2013]]-Tabla38101124172656[[#This Row],[2013]] -> 592560.25 | F2: =Tabla381011241726[[#This Row],[2014]]-Tabla38101124172656[[#This Row],[2014]] -> 550859.86 | G2: =Tabla381011241726[[#This Row],[2015]]-Tabla38101124172656[[#This Row],[2015]] -> 966088.56
A3: E-02 | B3: Empresa 2 | C3: =Tabla381011241726[[#This Row],[2011]]-Tabla38101124172656[[#This Row],[2011]] -> 51352 | D3: =Tabla381011241726[[#This Row],[2012]]-Tabla38101124172656[[#This Row],[2012]] -> -393162 | E3: =Tabla381011241726[[#This Row],[2013]]-Tabla38101124172656[[#This Row],[2013]] -> -162239 | F3: =Tabla381011241726[[#This Row],[2014]]-Tabla38101124172656[[#This Row],[2014]] -> 42905 | G3: =Tabla381011241726[[#This Row],[2015]]-Tabla38101124172656[[#This Row],[2015]] -> 51352
A4: E-03 | B4: Empresa 3 | C4: =Tabla381011241726[[#This Row],[2011]]-Tabla38101124172656[[#This Row],[2011]] -> 252706.1 | D4: =Tabla381011241726[[#This Row],[2012]]-Tabla38101124172656[[#This Row],[2012]] -> 230206.85 | E4: =Tabla381011241726[[#This Row],[2013]]-Tabla38101124172656[[#This Row],[2013]] -> 934363.02 | F4: =Tabla381011241726[[#This Row],[2014]]-Tabla38101124172656[[#This Row],[2014]] -> 1062537 | G4: =Tabla381011241726[[#This Row],[2015]]-Tabla38101124172656[[#This Row],[2015]] -> 925298
A5: E-04 | B5: Empresa 4 | C5: =Tabla381011241726[[#This Row],[2011]]-Tabla38101124172656[[#This Row],[2011]] -> 120098 | D5: =Tabla381011241726[[#This Row],[2012]]-Tabla38101124172656[[#This Row],[2012]] -> 206832 | E5: =Tabla381011241726[[#This Row],[2013]]-Tabla38101124172656[[#This Row],[2013]] -> 59243.17 | F5: =Tabla381011241726[[#This Row],[2014]]-Tabla38101124172656[[#This Row],[2014]] -> 234496.02 | G5: =Tabla381011241726[[#This Row],[2015]]-Tabla38101124172656[[#This Row],[2015]] -> 230104
A6: E-05 | B6: Empresa 5 | C6: =Tabla381011241726[[#This Row],[2011]]-Tabla38101124172656[[#This Row],[2011]] -> 39156 | D6: =Tabla381011241726[[#This Row],[2012]]-Tabla38101124172656[[#This Row],[2012]] -> 87438.34 | E6: =Tabla381011241726[[#This Row],[2013]]-Tabla38101124172656[[#This Row],[2013]] -> 62460.03 | F6: =Tabla381011241726[[#This Row],[2014]]-Tabla38101124172656[[#This Row],[2014]] -> 24777.02 | G6: =Tabla381011241726[[#This Row],[2015]]-Tabla38101124172656[[#This Row],[2015]] -> 235706
A7: E-06 | B7: Empresa 6 | E7: =Tabla381011241726[[#This Row],[2013]]-Tabla38101124172656[[#This Row],[2013]] -> 2232873 | F7: =Tabla381011241726[[#This Row],[2014]]-Tabla38101124172656[[#This Row],[2014]] -> 2232873 | G7: =Tabla381011241726[[#This Row],[2015]]-Tabla38101124172656[[#This Row],[2015]] -> 2232873
A8: E-07 | B8: Empresa 7 | C8: =Tabla381011241726[[#This Row],[2011]]-Tabla38101124172656[[#This Row],[2011]] -> -99800 | D8: =Tabla381011241726[[#This Row],[2012]]-Tabla38101124172656[[#This Row],[2012]] -> 83859.54 | E8: =Tabla381011241726[[#This Row],[2013]]-Tabla38101124172656[[#This Row],[2013]] -> 36145.448 | F8: =Tabla381011241726[[#This Row],[2014]]-Tabla38101124172656[[#This Row],[2014]] -> 111396.24 | G8: =Tabla381011241726[[#This Row],[2015]]-Tabla38101124172656[[#This Row],[2015]] -> 497236.91
A9: E-08 | B9: Empresa 8 | C9: =Tabla381011241726[[#This Row],[2011]]-Tabla38101124172656[[#This Row],[2011]] -> 270000 | D9: =Tabla381011241726[[#This Row],[2012]]-Tabla38101124172656[[#This Row],[2012]] -> 283000 | E9: =Tabla381011241726[[#This Row],[2013]]-Tabla38101124172656[[#This Row],[2013]] -> 411000 | F9: =Tabla381011241726[[#This Row],[2014]]-Tabla38101124172656[[#This Row],[2014]] -> 260000 | G9: =Tabla381011241726[[#This Row],[2015]]-Tabla38101124172656[[#This Row],[2015]] -> 270000
A10: E-09 | B10: Empresa 9 | C10: =Tabla381011241726[[#This Row],[2011]]-Tabla38101124172656[[#This Row],[2011]] -> 1200000 | D10: =Tabla381011241726[[#This Row],[2012]]-Tabla38101124172656[[#This Row],[2012]] -> 1600000 | E10: =Tabla381011241726[[#This Row],[2013]]-Tabla38101124172656[[#This Row],[2013]] -> 2000000 | F10: =Tabla381011241726[[#This Row],[2014]]-Tabla38101124172656[[#This Row],[2014]] -> 1010000 | G10: =Tabla381011241726[[#This Row],[2015]]-Tabla38101124172656[[#This Row],[2015]] -> 1050000
A11: E-10 | B11: Empresa 10 | C11: =Tabla381011241726[[#This Row],[2011]]-Tabla38101124172656[[#This Row],[2011]] -> 271512 | D11: =Tabla381011241726[[#This Row],[2012]]-Tabla38101124172656[[#This Row],[2012]] -> 320479 | E11: =Tabla381011241726[[#This Row],[2013]]-Tabla38101124172656[[#This Row],[2013]] -> 348145 | F11: =Tabla381011241726[[#This Row],[2014]]-Tabla38101124172656[[#This Row],[2014]] -> 393008 | G11: =Tabla381011241726[[#This Row],[2015]]-Tabla38101124172656[[#This Row],[2015]] -> 158403
A12: E-11 | B12: Empresa 11 | C12: =Tabla381011241726[[#This Row],[2011]]-Tabla38101124172656[[#This Row],[2011]] -> 501000 | D12: =Tabla381011241726[[#This Row],[2012]]-Tabla38101124172656[[#This Row],[2012]] -> 400594 | E12: =Tabla381011241726[[#This Row],[2013]]-Tabla38101124172656[[#This Row],[2013]] -> 120537.08 | F12: =Tabla381011241726[[#This Row],[2014]]-Tabla38101124172656[[#This Row],[2014]] -> 68812.74 | G12: =Tabla381011241726[[#This Row],[2015]]-Tabla38101124172656[[#This Row],[2015]] -> 278372
A13: E-12 | B13: Empresa 12 | C13: =Tabla381011241726[[#This Row],[2011]]-Tabla38101124172656[[#This Row],[2011]] -> 71758.71 | D13: =Tabla381011241726[[#This Row],[2012]]-Tabla38101124172656[[#This Row],[2012]] -> 165398.59 | E13: =Tabla381011241726[[#This Row],[2013]]-Tabla38101124172656[[#This Row],[2013]] -> 461542 | F13: =Tabla381011241726[[#This Row],[2014]]-Tabla38101124172656[[#This Row],[2014]] -> 383366 | G13: =Tabla381011241726[[#This Row],[2015]]-Tabla38101124172656[[#This Row],[2015]] -> 2062
A14: E-13 | B14: Empresa 13 | C14: =Tabla381011241726[[#This Row],[2011]]-Tabla38101124172656[[#This Row],[2011]] -> -50000 | D14: =Tabla381011241726[[#This Row],[2012]]-Tabla38101124172656[[#This Row],[2012]] -> -50000 | E14: =Tabla381011241726[[#This Row],[2013]]-Tabla38101124172656[[#This Row],[2013]] -> 20433 | F14: =Tabla381011241726[[#This Row],[2014]]-Tabla38101124172656[[#This Row],[2014]] -> 132248 | G14: =Tabla381011241726[[#This Row],[2015]]-Tabla38101124172656[[#This Row],[2015]] -> 295050
A15: E-14 | B15: Empresa 14 | D15: =Tabla381011241726[[#This Row],[2012]]-Tabla38101124172656[[#This Row],[2012]] -> 691484.28 | E15: =Tabla381011241726[[#This Row],[2013]]-Tabla38101124172656[[#This Row],[2013]] -> 755606.4 | F15: =Tabla381011241726[[#This Row],[2014]]-Tabla38101124172656[[#This Row],[2014]] -> 759181.56 | G15: =Tabla381011241726[[#This Row],[2015]]-Tabla38101124172656[[#This Row],[2015]] -> 297383
A16: E-15 | B16: Empresa 15 | C16: =Tabla381011241726[[#This Row],[2011]]-Tabla38101124172656[[#This Row],[2011]] -> 33315 | D16: =Tabla381011241726[[#This Row],[2012]]-Tabla38101124172656[[#This Row],[2012]] -> 240732 | E16: =Tabla381011241726[[#This Row],[2013]]-Tabla38101124172656[[#This Row],[2013]] -> 338135.95 | F16: =Tabla381011241726[[#This Row],[2014]]-Tabla38101124172656[[#This Row],[2014]] -> 234490.87 | G16: =Tabla381011241726[[#This Row],[2015]]-Tabla38101124172656[[#This Row],[2015]] -> 700000
A17: E-16 | B17: Empresa 16 | C17: =Tabla381011241726[[#This Row],[2011]]-Tabla38101124172656[[#This Row],[2011]] -> -91000 | D17: =Tabla381011241726[[#This Row],[2012]]-Tabla38101124172656[[#This Row],[2012]] -> 144690.21 | E17: =Tabla381011241726[[#This Row],[2013]]-Tabla38101124172656[[#This Row],[2013]] -> 156674.29 | F17: =Tabla381011241726[[#This Row],[2014]]-Tabla38101124172656[[#This Row],[2014]] -> 203437.47 | G17: =Tabla381011241726[[#This Row],[2015]]-Tabla38101124172656[[#This Row],[2015]] -> 263694
A18: E-17 | B18: Empresa 17 | F18: =Tabla381011241726[[#This Row],[2014]]-Tabla38101124172656[[#This Row],[2014]] -> 16217 | G18: =Tabla381011241726[[#This Row],[2015]]-Tabla38101124172656[[#This Row],[2015]] -> 397703
A19: E-18 | B19: Empresa 18 | C19: =Tabla381011241726[[#This Row],[2011]]-Tabla38101124172656[[#This Row],[2011]] -> 259397.74 | D19: =Tabla381011241726[[#This Row],[2012]]-Tabla38101124172656[[#This Row],[2012]] -> 395022.07 | E19: =Tabla381011241726[[#This Row],[2013]]-Tabla38101124172656[[#This Row],[2013]] -> 658503.26 | F19: =Tabla381011241726[[#This Row],[2014]]-Tabla38101124172656[[#This Row],[2014]] -> 852533.31 | G19: =Tabla381011241726[[#This Row],[2015]]-Tabla38101124172656[[#This Row],[2015]] -> 390847
A20: E-19 | B20: Empresa 19 | C20: =Tabla381011241726[[#This Row],[2011]]-Tabla38101124172656[[#This Row],[2011]] -> 9900 | D20: =Tabla381011241726[[#This Row],[2012]]-Tabla38101124172656[[#This Row],[2012]] -> 200999 | E20: =Tabla381011241726[[#This Row],[2013]]-Tabla38101124172656[[#This Row],[2013]] -> 80000 | F20: =Tabla381011241726[[#This Row],[2014]]-Tabla38101124172656[[#This Row],[2014]] -> 400000 | G20: =Tabla381011241726[[#This Row],[2015]]-Tabla38101124172656[[#This Row],[2015]] -> -2040782
A21: E-20 | B21: Empresa 20 | C21: =Tabla381011241726[[#This Row],[2011]]-Tabla38101124172656[[#This Row],[2011]] -> -99805 | D21: =Tabla381011241726[[#This Row],[2012]]-Tabla38101124172656[[#This Row],[2012]] -> 119999 | E21: =Tabla381011241726[[#This Row],[2013]]-Tabla38101124172656[[#This Row],[2013]] -> -98990 | F21: =Tabla381011241726[[#This Row],[2014]]-Tabla38101124172656[[#This Row],[2014]] -> -200030 | G21: =Tabla381011241726[[#This Row],[2015]]-Tabla38101124172656[[#This Row],[2015]] -> 221041

Sheet Empresas
A1: COD | B1: Nombres | C1: Apellidos | D1: Empresa | E1: Industry
A2: E-01 | B2: Olga | C2: Rivera | D2: Empresa 1 | E2: Service
A3: E-02 | B3: Pablo | C3: Barrientos | D3: Empresa 2 | E3: Service
A4: E-03 | B4: Luisa | C4: Lopez | D4: Empresa 3 | E4: Manu
A5: E-04 | B5: Jose | C5: Armas | D5: Empresa 4 | E5: Cons
A6: E-05 | B6: Ana Beatriz | C6: Polanco | D6: Empresa 5 | E6: Food
A7: E-06 | B7: Carlos | C7: Corzo | D7: Empresa 6 | E7: Service
A8: E-07 | B8: Andrez | C8: Ruiz | D8: Empresa 7 | E8: Cons
A9: E-08 | B9: Byron | C9: Azmitia | D9: Empresa 8 | E9: Food
A10: E-09 | B10: Edgar | C10: Perez | D10: Empresa 9 | E10: Tech
A11: E-10 | B11: Alejadro | C11: Bran | D11: Empresa 10 | E11: Food
A12: E-11 | B12: Mariana | C12: Ortiz | D12: Empresa 11 | E12: Service
... A21: E-20 | B21: Jacqueline | C21: Cifuentes | D21: Empresa 20 | E21: Food
C26: Women | D26: Men
B27: 2011 | C27: ='Summary FR'!C5 -> 0 | D27: ='Summary FR'!C6 -> 0
B28: 2012 | C28: 10 | D28: ='Summary FR'!D6 -> 0
B29: 2013 | C29: ='Summary FR'!E5 -> 0 | D29: 15
B30: 2014 | C30: ='Summary FR'!F5 -> 0 | D30: ='Summary FR'!F6 -> 0
B31: 2015 | C31: ='Summary FR'!G5 -> 0 | D31: ='Summary FR'!G6 -> 0

Sheet Ejemplos posibles
